{
    "id": "<!doctype html>\n<html lang=en>\n<title>500 Internal Server Error</title>\n<h1>Internal Server Error</h1>\n<p>The server encountered an internal error and was unable to complete your request. Either the server is overloaded or there is an error in the application.</p>\n",
    "pairs": [
        {
            "category": "Comedy",
            "pairID": 0,
            "pairLevel": "medium-low",
            "video1": "7325810109223800110",
            "video1Level": "low",
            "video2": "7327772369102179626",
            "video2Level": "medium"
        },
        {
            "category": "Comedy",
            "pairID": 1,
            "pairLevel": "medium-very_low",
            "video1": "7329550366432070958",
            "video1Level": "very_low",
            "video2": "7327772369102179626",
            "video2Level": "medium"
        },
        {
            "category": "Comedy",
            "pairID": 2,
            "pairLevel": "medium-low",
            "video1": "7322576916073024814",
            "video1Level": "medium",
            "video2": "7325810109223800110",
            "video2Level": "low"
        },
        {
            "category": "Comedy",
            "pairID": 3,
            "pairLevel": "medium-very_low",
            "video1": "7329550366432070958",
            "video1Level": "very_low",
            "video2": "7322576916073024814",
            "video2Level": "medium"
        },
        {
            "category": "Comedy",
            "pairID": 4,
            "pairLevel": "medium-low",
            "video1": "7325810109223800110",
            "video1Level": "low",
            "video2": "7322576916073024814",
            "video2Level": "medium"
        },
        {
            "category": "Comedy",
            "pairID": 5,
            "pairLevel": "medium-very_low",
            "video1": "7322576916073024814",
            "video1Level": "medium",
            "video2": "7329550366432070958",
            "video2Level": "very_low"
        },
        {
            "category": "Comedy",
            "pairID": 6,
            "pairLevel": "low-very_low",
            "video1": "7325810109223800110",
            "video1Level": "low",
            "video2": "7329550366432070958",
            "video2Level": "very_low"
        }
    ],
    "videos": [
        {
            "category": "Comedy",
            "comment_count": 3,
            "create_time": 1706717700,
            "id": "7329550366432070958",
            "like_count": 374,
            "share_count": 0,
            "username": "josiah.t.b",
            "video_description": "BEST of @austenwestend #theatre #musicaltheatre #theatrelife #theatrekid #theatrekids #livetheatre #theatrelove",
            "view_count": 25
        },
        {
            "category": "Comedy",
            "comment_count": 11390,
            "create_time": 1706130004,
            "id": "7327772369102179626",
            "like_count": 331864,
            "share_count": 4840,
            "username": "americanhighshorts",
            "video_description": "first kid who looks is a goner #americanhighshorts #schoolday #highschoollife #class ",
            "view_count": 525756
        },
        {
            "category": "Comedy",
            "comment_count": 404,
            "create_time": 1705673097,
            "id": "7325810109223800110",
            "like_count": 22968,
            "share_count": 58,
            "username": "jay.and.neo",
            "video_description": "Replying to @shatirriegipson Our kid knows he left NO CRUMBS & we're so proud of him. Can't wait to see his growth!",
            "view_count": 16625
        },
        {
            "category": "Comedy",
            "comment_count": 14878,
            "create_time": 1704920330,
            "id": "7322576916073024814",
            "like_count": 597885,
            "share_count": 5264,
            "username": "americanhighshorts",
            "video_description": "looks like they didn\u2019t study #americanhighshorts #test #finalexams #midterm #study #students ",
            "view_count": 574488
        },
        {
            "category": "Comedy",
            "comment_count": 14878,
            "create_time": 1704920330,
            "id": "7322576916073024814",
            "like_count": 597885,
            "share_count": 5264,
            "username": "americanhighshorts",
            "video_description": "looks like they didn\u2019t study #americanhighshorts #test #finalexams #midterm #study #students ",
            "view_count": 574488
        }
    ]
}